{
  "_id": { "$oid": "684d46ca0e52b15aba516162" },
  "Prices": [
    {
      "Name": "Screen",
      "Quantity": "100",
      "PriceDetails": [
        {
          "Type": "Product",
          "Description": "Printed 1 Colour 1 Side (per product)",
          "Value": "0.80",
          "Unit": "Per Unit"
        },
        {
          "Type": "Additional Charge",
          "Description": "Additional Print Charge per Colour per Position (per unit)",
          "Value": "0.02",
          "Unit": "Per Unit"
        },
        {
          "Type": "Setup",
          "Description": "Print Set Up per Colour (total)",
          "Value": "20.00",
          "Unit": "Total"
        },
        {
          "Type": "Additional Charge",
          "Description": "Pantone Charge (total)",
          "Value": "25.00",
          "Unit": "Total"
        },
        {
          "Type": "Carriage",
          "Description": "Carriage to 1 UK Mainland Address (total)*Exc.Highlands",
          "Value": "10.00",
          "Unit": "Total"
        }
      ]
    },
    {
      "Name": "Screen",
      "Quantity": "250",
      "PriceDetails": [
        {
          "Type": "Product",
          "Description": "Printed 1 Colour 1 Side (per product)",
          "Value": "0.63",
          "Unit": "Per Unit"
        },
        {
          "Type": "Additional Charge",
          "Description": "Additional Print Charge per Colour per Position (per unit)",
          "Value": "0.02",
          "Unit": "Per Unit"
        },
        {
          "Type": "Setup",
          "Description": "Print Set Up per Colour (total)",
          "Value": "20.00",
          "Unit": "Total"
        },
        {
          "Type": "Additional Charge",
          "Description": "Pantone Charge (total)",
          "Value": "25.00",
          "Unit": "Total"
        },
        {
          "Type": "Carriage",
          "Description": "Carriage to 1 UK Mainland Address (total)*Exc.Highlands",
          "Value": "10.00",
          "Unit": "Total"
        }
      ]
    },
    {
      "Name": "Screen",
      "Quantity": "500",
      "PriceDetails": [
        {
          "Type": "Product",
          "Description": "Printed 1 Colour 1 Side (per product)",
          "Value": "0.55",
          "Unit": "Per Unit"
        },
        {
          "Type": "Additional Charge",
          "Description": "Additional Print Charge per Colour per Position (per unit)",
          "Value": "0.02",
          "Unit": "Per Unit"
        },
        {
          "Type": "Setup",
          "Description": "Print Set Up per Colour (total)",
          "Value": "20.00",
          "Unit": "Total"
        },
        {
          "Type": "Additional Charge",
          "Description": "Pantone Charge (total)",
          "Value": "25.00",
          "Unit": "Total"
        },
        {
          "Type": "Carriage",
          "Description": "Carriage to 1 UK Mainland Address (total)*Exc.Highlands",
          "Value": "10.00",
          "Unit": "Total"
        }
      ]
    },
    {
      "Name": "Screen",
      "Quantity": "1000",
      "PriceDetails": [
        {
          "Type": "Product",
          "Description": "Printed 1 Colour 1 Side (per product)",
          "Value": "0.42",
          "Unit": "Per Unit"
        },
        {
          "Type": "Additional Charge",
          "Description": "Additional Print Charge per Colour per Position (per unit)",
          "Value": "0.02",
          "Unit": "Per Unit"
        },
        {
          "Type": "Setup",
          "Description": "Print Set Up per Colour (total)",
          "Value": "20.00",
          "Unit": "Total"
        },
        {
          "Type": "Additional Charge",
          "Description": "Pantone Charge (total)",
          "Value": "25.00",
          "Unit": "Total"
        },
        {
          "Type": "Carriage",
          "Description": "Carriage to 1 UK Mainland Address (total)*Exc.Highlands",
          "Value": "10.00",
          "Unit": "Total"
        }
      ]
    },
    {
      "Name": "Screen",
      "Quantity": "2500",
      "PriceDetails": [
        {
          "Type": "Product",
          "Description": "Printed 1 Colour 1 Side (per product)",
          "Value": "0.41",
          "Unit": "Per Unit"
        },
        {
          "Type": "Additional Charge",
          "Description": "Additional Print Charge per Colour per Position (per unit)",
          "Value": "0.02",
          "Unit": "Per Unit"
        },
        {
          "Type": "Setup",
          "Description": "Print Set Up per Colour (total)",
          "Value": "0.00",
          "Unit": "Total"
        },
        {
          "Type": "Additional Charge",
          "Description": "Pantone Charge (total)",
          "Value": "0.00",
          "Unit": "Total"
        },
        {
          "Type": "Carriage",
          "Description": "Carriage to 1 UK Mainland Address (total)*Exc.Highlands",
          "Value": "24.00",
          "Unit": "Total"
        }
      ]
    },
    {
      "Name": "Screen",
      "Quantity": "5000",
      "PriceDetails": [
        {
          "Type": "Product",
          "Description": "Printed 1 Colour 1 Side (per product)",
          "Value": "0.38",
          "Unit": "Per Unit"
        },
        {
          "Type": "Additional Charge",
          "Description": "Additional Print Charge per Colour per Position (per unit)",
          "Value": "0.02",
          "Unit": "Per Unit"
        },
        {
          "Type": "Setup",
          "Description": "Print Set Up per Colour (total)",
          "Value": "0.00",
          "Unit": "Total"
        },
        {
          "Type": "Additional Charge",
          "Description": "Pantone Charge (total)",
          "Value": "0.00",
          "Unit": "Total"
        },
        {
          "Type": "Carriage",
          "Description": "Carriage to 1 UK Mainland Address (total)*Exc.Highlands",
          "Value": "40.00",
          "Unit": "Total"
        }
      ]
    },
    {
      "Name": "Screen",
      "Quantity": "10000",
      "PriceDetails": [
        {
          "Type": "Product",
          "Description": "Printed 1 Colour 1 Side (per product)",
          "Value": "0.37",
          "Unit": "Per Unit"
        },
        {
          "Type": "Additional Charge",
          "Description": "Additional Print Charge per Colour per Position (per unit)",
          "Value": "0.02",
          "Unit": "Per Unit"
        },
        {
          "Type": "Setup",
          "Description": "Print Set Up per Colour (total)",
          "Value": "0.00",
          "Unit": "Total"
        },
        {
          "Type": "Additional Charge",
          "Description": "Pantone Charge (total)",
          "Value": "0.00",
          "Unit": "Total"
        },
        {
          "Type": "Carriage",
          "Description": "Carriage to 1 UK Mainland Address (total)*Exc.Highlands",
          "Value": "70.00",
          "Unit": "Total"
        }
      ]
    },
    {
      "Name": "Screen",
      "Quantity": "25000",
      "PriceDetails": [
        {
          "Type": "Product",
          "Description": "Printed 1 Colour 1 Side (per product)",
          "Value": "0.36",
          "Unit": "Per Unit"
        },
        {
          "Type": "Additional Charge",
          "Description": "Additional Print Charge per Colour per Position (per unit)",
          "Value": "0.02",
          "Unit": "Per Unit"
        },
        {
          "Type": "Setup",
          "Description": "Print Set Up per Colour (total)",
          "Value": "0.00",
          "Unit": "Total"
        },
        {
          "Type": "Additional Charge",
          "Description": "Pantone Charge (total)",
          "Value": "0.00",
          "Unit": "Total"
        },
        {
          "Type": "Carriage",
          "Description": "Carriage to 1 UK Mainland Address (total)*Exc.Highlands",
          "Value": "110.00",
          "Unit": "Total"
        }
      ]
    }
  ],
  "LeadTime": "15 working days",
  "EndUserWebsite": "https://www.promobestsellers.co.uk/product/10mm-plant-silk-lanyard",
  "Colors": ["off-white", "pantone matched at an additional cost"],
  "CatalogueId": "41",
  "CatalogueName": "Lanyards"
}
